odoo/addons/mrp_workcenter_workorder_link/README.rst
odoo/addons/mrp_workcenter_workorder_link/__init__.py
odoo/addons/mrp_workcenter_workorder_link/__manifest__.py
odoo/addons/mrp_workcenter_workorder_link/i18n/it.po
odoo/addons/mrp_workcenter_workorder_link/i18n/mrp_workcenter_workorder_link.pot
odoo/addons/mrp_workcenter_workorder_link/models/__init__.py
odoo/addons/mrp_workcenter_workorder_link/models/mrp_workcenter.py
odoo/addons/mrp_workcenter_workorder_link/models/mrp_workorder.py
odoo/addons/mrp_workcenter_workorder_link/readme/CONTRIBUTORS.rst
odoo/addons/mrp_workcenter_workorder_link/readme/DESCRIPTION.rst
odoo/addons/mrp_workcenter_workorder_link/static/description/icon.png
odoo/addons/mrp_workcenter_workorder_link/static/description/index.html
odoo/addons/mrp_workcenter_workorder_link/tests/__init__.py
odoo/addons/mrp_workcenter_workorder_link/tests/test_action.py
odoo/addons/mrp_workcenter_workorder_link/views/mrp_workcenter_views.xml
odoo/addons/mrp_workcenter_workorder_link/views/mrp_workorder_views.xml
odoo_addon_mrp_workcenter_workorder_link-16.0.1.0.0.6.dist-info/METADATA
odoo_addon_mrp_workcenter_workorder_link-16.0.1.0.0.6.dist-info/WHEEL
odoo_addon_mrp_workcenter_workorder_link-16.0.1.0.0.6.dist-info/top_level.txt
odoo_addon_mrp_workcenter_workorder_link-16.0.1.0.0.6.dist-info/RECORD
